inlog/Logger.py
inlog/Tree.py
inlog/__init__.py
inlog/flowchart.py
inlog/loaders.py
inlog-2.2.3.dist-info/LICENSE
inlog-2.2.3.dist-info/METADATA
inlog-2.2.3.dist-info/WHEEL
inlog-2.2.3.dist-info/entry_points.txt
inlog-2.2.3.dist-info/top_level.txt
inlog-2.2.3.dist-info/RECORD
