Metadata-Version: 2.1
Name: inlog
Version: 2.2.3
Summary: Keep track of your data! Reading config files and creating comprehensive logs for your results.
Author-email: Paul Ockenfuß <paul.ockenfuss@physik.uni-muenchen.de>
License: inlog © 2023 by Paul Ockenfuß is licensed under CC BY-SA 4.0. To view a copy of this license, visit http://creativecommons.org/licenses/by-sa/4.0/
Project-URL: Homepage, https://github.com/Ockenfuss/inlog
Keywords: config,ini,log,yaml
Classifier: Programming Language :: Python
Classifier: Programming Language :: Python :: 3
Classifier: Intended Audience :: Science/Research
Classifier: Topic :: Software Development :: Version Control
Classifier: Topic :: Software Development :: Quality Assurance
Classifier: Topic :: System :: Logging
Requires-Python: >=3.8
License-File: LICENSE
Provides-Extra: extra
Requires-Dist: pyyaml ; extra == 'extra'
